{"name":"Regexppreviewer","tagline":"A simple GUI for checking regular expression at real-time","body":"# RegExpPreviewer\r\nA simple UI for checking regular expression\r\n\r\n# Motivation\r\nPeople usually are not familiar with regular expression enough. Therefore, a small \"Test.java\" would be created to see if the regexp coming out from your brain is correct. With this small program, you can paste your doc to match and input your regexp in the bottom field. This program would highlight the matched strings to help you correct regexp immediately.\r\n\r\n![Alt text](http://i.imgur.com/3zFu5K0.png?1 \"Screenshot\")\r\n","google":"","note":"Don't delete this file! It's used internally to help with page regeneration."}